sphinxcontrib_translation_assistant-0.1.2-py3.6-nspkg.pth
sphinxcontrib/translation_assistant.py
sphinxcontrib_translation_assistant-0.1.2.dist-info/DESCRIPTION.rst
sphinxcontrib_translation_assistant-0.1.2.dist-info/METADATA
sphinxcontrib_translation_assistant-0.1.2.dist-info/RECORD
sphinxcontrib_translation_assistant-0.1.2.dist-info/WHEEL
sphinxcontrib_translation_assistant-0.1.2.dist-info/metadata.json
sphinxcontrib_translation_assistant-0.1.2.dist-info/namespace_packages.txt
sphinxcontrib_translation_assistant-0.1.2.dist-info/top_level.txt
