Metadata-Version: 2.0
Name: sphinxcontrib-translation-assistant
Version: 0.1.2
Summary: Sphinx extension to view Translation Assistant file
Home-page: https://github.com/julot/sphinxcontrib-translation-assistant
Author: Andy Yulius
Author-email: julot@gmail.com
License: MIT
Keywords: sphinx sphinxcontrib translation assistant
Platform: any
Classifier: Development Status :: 3 - Alpha
Classifier: Environment :: Console
Classifier: Intended Audience :: Developers
Classifier: License :: OSI Approved :: MIT License
Classifier: Operating System :: OS Independent
Classifier: Programming Language :: Python
Classifier: Topic :: Documentation
Classifier: Topic :: Utilities
Requires-Dist: Sphinx (>=0.6)
